package org.lolhens.asmpatcher

import java.util

import org.lolhens.asmpatcher.Insn._

import scala.collection.JavaConversions._

/**
 * Created by LolHens on 14.12.2014.
 */
class Insn(name: String, opcode: Int) {
  insns += name -> this

  override def toString = name

  def getType = opcode
}

object Insn {
  val insns = new util.HashMap[String, Insn]()

  val NOP = new Insn("nop", 0)
  val ACONST_NULL = new Insn("aconst_null", 1)
  val ICONST_M1 = new Insn("iconst_m1", 2)
  val ICONST_0 = new Insn("iconst_0", 3)
  val ICONST_1 = new Insn("iconst_1", 4)
  val ICONST_2 = new Insn("iconst_2", 5)
  val ICONST_3 = new Insn("iconst_3", 6)
  val ICONST_4 = new Insn("iconst_4", 7)
  val ICONST_5 = new Insn("iconst_5", 8)
  val LCONST_0 = new Insn("lconst_0", 9)
  val LCONST_1 = new Insn("lconst_1", 10)
  val FCONST_0 = new Insn("fconst_0", 11)
  val FCONST_1 = new Insn("fconst_1", 12)
  val FCONST_2 = new Insn("fconst_2", 13)
  val DCONST_0 = new Insn("dconst_0", 14)
  val DCONST_1 = new Insn("dconst_1", 15)
  val BIPUSH = new Insn("bipush", 16)
  val SIPUSH = new Insn("sipush", 17)
  val LDC = new Insn("ldc", 18)
  val LDC_W = new Insn("ldc_w", 19)
  val LDC2_W = new Insn("ldc2_w", 20)
  val ILOAD = new Insn("iload", 21)
  val LLOAD = new Insn("lload", 22)
  val FLOAD = new Insn("fload", 23)
  val DLOAD = new Insn("dload", 24)
  val ALOAD = new Insn("aload", 25)
  val ILOAD_0 = new Insn("iload_0", 26)
  val ILOAD_1 = new Insn("iload_1", 27)
  val ILOAD_2 = new Insn("iload_2", 28)
  val ILOAD_3 = new Insn("iload_3", 29)
  val LLOAD_0 = new Insn("lload_0", 30)
  val LLOAD_1 = new Insn("lload_1", 31)
  val LLOAD_2 = new Insn("lload_2", 32)
  val LLOAD_3 = new Insn("lload_3", 33)
  val FLOAD_0 = new Insn("fload_0", 34)
  val FLOAD_1 = new Insn("fload_1", 35)
  val FLOAD_2 = new Insn("fload_2", 36)
  val FLOAD_3 = new Insn("fload_3", 37)
  val DLOAD_0 = new Insn("dload_0", 38)
  val DLOAD_1 = new Insn("dload_1", 39)
  val DLOAD_2 = new Insn("dload_2", 40)
  val DLOAD_3 = new Insn("dload_3", 41)
  val ALOAD_0 = new Insn("aload_0", 42)
  val ALOAD_1 = new Insn("aload_1", 43)
  val ALOAD_2 = new Insn("aload_2", 44)
  val ALOAD_3 = new Insn("aload_3", 45)
  val IALOAD = new Insn("iaload", 46)
  val LALOAD = new Insn("laload", 47)
  val FALOAD = new Insn("faload", 48)
  val DALOAD = new Insn("daload", 49)
  val AALOAD = new Insn("aaload", 50)
  val BALOAD = new Insn("baload", 51)
  val CALOAD = new Insn("caload", 52)
  val SALOAD = new Insn("saload", 53)
  val ISTORE = new Insn("istore", 54)
  val LSTORE = new Insn("lstore", 55)
  val FSTORE = new Insn("fstore", 56)
  val DSTORE = new Insn("dstore", 57)
  val ASTORE = new Insn("astore", 58)
  val ISTORE_0 = new Insn("istore_0", 59)
  val ISTORE_1 = new Insn("istore_1", 60)
  val ISTORE_2 = new Insn("istore_2", 61)
  val ISTORE_3 = new Insn("istore_3", 62)
  val LSTORE_0 = new Insn("lstore_0", 63)
  val LSTORE_1 = new Insn("lstore_1", 64)
  val LSTORE_2 = new Insn("lstore_2", 65)
  val LSTORE_3 = new Insn("lstore_3", 66)
  val FSTORE_0 = new Insn("fstore_0", 67)
  val FSTORE_1 = new Insn("fstore_1", 68)
  val FSTORE_2 = new Insn("fstore_2", 69)
  val FSTORE_3 = new Insn("fstore_3", 70)
  val DSTORE_0 = new Insn("dstore_0", 71)
  val DSTORE_1 = new Insn("dstore_1", 72)
  val DSTORE_2 = new Insn("dstore_2", 73)
  val DSTORE_3 = new Insn("dstore_3", 74)
  val ASTORE_0 = new Insn("astore_0", 75)
  val ASTORE_1 = new Insn("astore_1", 76)
  val ASTORE_2 = new Insn("astore_2", 77)
  val ASTORE_3 = new Insn("astore_3", 78)
  val IASTORE = new Insn("iastore", 79)
  val LASTORE = new Insn("lastore", 80)
  val FASTORE = new Insn("fastore", 81)
  val DASTORE = new Insn("dastore", 82)
  val AASTORE = new Insn("aastore", 83)
  val BASTORE = new Insn("bastore", 84)
  val CASTORE = new Insn("castore", 85)
  val SASTORE = new Insn("sastore", 86)
  val POP = new Insn("pop", 87)
  val POP2 = new Insn("pop2", 88)
  val DUP = new Insn("dup", 89)
  val DUP_X1 = new Insn("dup_x1", 90)
  val DUP_X2 = new Insn("dup_x2", 91)
  val DUP2 = new Insn("dup2", 92)
  val DUP2_X1 = new Insn("dup2_x1", 93)
  val DUP2_X2 = new Insn("dup2_x2", 94)
  val SWAP = new Insn("swap", 95)
  val IADD = new Insn("iadd", 96)
  val LADD = new Insn("ladd", 97)
  val FADD = new Insn("fadd", 98)
  val DADD = new Insn("dadd", 99)
  val ISUB = new Insn("isub", 100)
  val LSUB = new Insn("lsub", 101)
  val FSUB = new Insn("fsub", 102)
  val DSUB = new Insn("dsub", 103)
  val IMUL = new Insn("imul", 104)
  val LMUL = new Insn("lmul", 105)
  val FMUL = new Insn("fmul", 106)
  val DMUL = new Insn("dmul", 107)
  val IDIV = new Insn("idiv", 108)
  val LDIV = new Insn("ldiv", 109)
  val FDIV = new Insn("fdiv", 110)
  val DDIV = new Insn("ddiv", 111)
  val IREM = new Insn("irem", 112)
  val LREM = new Insn("lrem", 113)
  val FREM = new Insn("frem", 114)
  val DREM = new Insn("drem", 115)
  val INEG = new Insn("ineg", 116)
  val LNEG = new Insn("lneg", 117)
  val FNEG = new Insn("fneg", 118)
  val DNEG = new Insn("dneg", 119)
  val ISHL = new Insn("ishl", 120)
  val LSHL = new Insn("lshl", 121)
  val ISHR = new Insn("ishr", 122)
  val LSHR = new Insn("lshr", 123)
  val IUSHR = new Insn("iushr", 124)
  val LUSHR = new Insn("lushr", 125)
  val IAND = new Insn("iand", 126)
  val LAND = new Insn("land", 127)
  val IOR = new Insn("ior", 128)
  val LOR = new Insn("lor", 129)
  val IXOR = new Insn("ixor", 130)
  val LXOR = new Insn("lxor", 131)
  val IINC = new Insn("iinc", 132)
  val I2L = new Insn("i2l", 133)
  val I2F = new Insn("i2f", 134)
  val I2D = new Insn("i2d", 135)
  val L2I = new Insn("l2i", 136)
  val L2F = new Insn("l2f", 137)
  val L2D = new Insn("l2d", 138)
  val F2I = new Insn("f2i", 139)
  val F2L = new Insn("f2l", 140)
  val F2D = new Insn("f2d", 141)
  val D2I = new Insn("d2i", 142)
  val D2L = new Insn("d2l", 143)
  val D2F = new Insn("d2f", 144)
  val I2B = new Insn("i2b", 145)
  val I2C = new Insn("i2c", 146)
  val I2S = new Insn("i2s", 147)
  val LCMP = new Insn("lcmp", 148)
  val FCMPL = new Insn("fcmpl", 149)
  val FCMPG = new Insn("fcmpg", 150)
  val DCMPL = new Insn("dcmpl", 151)
  val DCMPG = new Insn("dcmpg", 152)
  val IFEQ = new Insn("ifeq", 153)
  val IFNE = new Insn("ifne", 154)
  val IFLT = new Insn("iflt", 155)
  val IFGE = new Insn("ifge", 156)
  val IFGT = new Insn("ifgt", 157)
  val IFLE = new Insn("ifle", 158)
  val IF_ICMPQ = new Insn("if_icmpeq", 159)
  val IF_AMPNE = new Insn("if_acmpne", 160)
  val IF_ICMPLT = new Insn("if_icmplt", 161)
  val IF_CMPGE = new Insn("if_icmpge", 162)
  val IF_ICMPGT = new Insn("if_icmpgt", 163)
  val IF_ICMPLE = new Insn("if_icmple", 164)
  val IF_ACMPEQ = new Insn("if_acmpeq", 165)
  val IF_ACMPNE = new Insn("if_acmpne", 166)
  val GOTO = new Insn("goto", 167)
  val JSR = new Insn("jsr", 168)
  val RET = new Insn("ret", 169)
  val TABLESWITCH = new Insn("tableswitch", 170)
  val LOOKUPSWITCH = new Insn("lookupswitch", 171)
  val IRETURN = new Insn("ireturn", 172)
  val LRETURN = new Insn("lreturn", 173)
  val FRETURN = new Insn("freturn", 174)
  val DRETURN = new Insn("dreturn", 175)
  val ARETURN = new Insn("areturn", 176)
  val RETURN = new Insn("return", 177)
  val GETSTATIC = new Insn("getstatic", 178)
  val PUTSTATIC = new Insn("putstatic", 179)
  val GETFIELD = new Insn("getfield", 180)
  val PUTFIELD = new Insn("putfield", 181)
  val INVOKEVIRTUAL = new Insn("invokevirtual", 182)
  val INVOKESPECIAL = new Insn("invokespecial", 183)
  val INVOKESTATIC = new Insn("invokestatic", 184)
  val INVOKEINTERFACE = new Insn("invokeinterface", 185)
  val UNUSED = new Insn("unused", 186)
  val NEW = new Insn("new", 187)
  val NEWARRAY = new Insn("newarray", 188)
  val ANEWARRAY = new Insn("anewarray", 189)
  val ARRAYLENGTH = new Insn("arraylength", 190)
  val ATHROW = new Insn("athrow", 191)
  val CHECKCAST = new Insn("checkcast", 192)
  val INSTANCEOF = new Insn("instanceof", 193)
  val MONITORENTER = new Insn("monitorenter", 194)
  val MONITOREXIT = new Insn("monitorexit", 195)
  val WIDE = new Insn("wide", 196)
  val MULTIANEWARRAY = new Insn("multianewarray", 197)
  val IFNULL = new Insn("ifnull", 198)
  val IFNONNULL = new Insn("ifnonnull", 199)
  val GOTO_W = new Insn("goto_w", 200)
  val JSR_W = new Insn("jsr_w", 201)
  val BREAKPOINT = new Insn("breakpoint", 202)
  val IMPDEP1 = new Insn("impdep1", 254)
  val IMPDEP2 = new Insn("impdep2", 255)
}
